gql_social_auth/__init__.py
gql_social_auth/constants.py
gql_social_auth/decorators.py
gql_social_auth/mixins.py
gql_social_auth/mutations.py
gql_social_auth/pipeline.py
gql_social_auth/types.py
gql_social_auth/utils.py
strawberry_django_social_auth-0.4.3.dist-info/LICENSE
strawberry_django_social_auth-0.4.3.dist-info/METADATA
strawberry_django_social_auth-0.4.3.dist-info/WHEEL
strawberry_django_social_auth-0.4.3.dist-info/RECORD
