Metadata-Version: 2.1
Name: strawberry-django-social-auth
Version: 0.4.3
Summary: Graphql Social authentication system with Strawberry for Django.
License: MIT
Author: Shritesh Jamulkar
Author-email: shritesh.sj@gmail.com
Maintainer: Shritesh Jamulkar
Maintainer-email: shritesh.sj@gmail.com
Requires-Python: >=3.8,<3.13
Classifier: Environment :: Web Environment
Classifier: Framework :: Django
Classifier: Framework :: Django :: 3.2
Classifier: Framework :: Django :: 4.1
Classifier: Intended Audience :: Developers
Classifier: License :: OSI Approved :: MIT License
Classifier: Operating System :: OS Independent
Classifier: Programming Language :: Python :: 3
Classifier: Programming Language :: Python :: 3.8
Classifier: Programming Language :: Python :: 3.9
Classifier: Programming Language :: Python :: 3.10
Classifier: Programming Language :: Python :: 3.11
Classifier: Programming Language :: Python :: 3.12
Requires-Dist: Django (>=3.2,<6)
Requires-Dist: PyJWT (>=2.6.0,<3.0)
Requires-Dist: promise (>=2.3,<3.0)
Requires-Dist: social-auth-app-django (>=2.1.0)
Requires-Dist: strawberry-django-auth (>=0.373.1)
Requires-Dist: strawberry-graphql-django (>=0.10.5)
Project-URL: Documentation, https://github.com/shritesh99/strawberry-django-social-auth
Project-URL: Homepage, https://github.com/shritesh99/strawberry-django-social-auth
